LICENSE
MANIFEST.in
README.md
setup.cfg
setup.py
awesomedecorators/__init__.py
awesomedecorators/memoized.py
awesomedecorators/timer.py
awesomedecorators/timez.py
python_awesome_decorators.egg-info/PKG-INFO
python_awesome_decorators.egg-info/SOURCES.txt
python_awesome_decorators.egg-info/dependency_links.txt
python_awesome_decorators.egg-info/requires.txt
python_awesome_decorators.egg-info/top_level.txt
tests/__init__.py
tests/tests.py