Metadata-Version: 1.1
Name: python-awesome-decorators
Version: 0.1.2
Summary: List of useful decorators in Python.
Home-page: https://github.com/romaryd/python-awesome-decorators
Author: Romary Dupuis
Author-email: romary@me.com
License: The MIT License (MIT)
